{
	"name": "pgmpcdctestpipeline",
	"properties": {
		"activities": [
			{
				"name": "DF_BALD0297_BTT_DIM",
				"type": "ExecuteDataFlow",
				"dependsOn": [],
				"policy": {
					"timeout": "1.00:00:00",
					"retry": 0,
					"retryIntervalInSeconds": 30,
					"secureOutput": false,
					"secureInput": false
				},
				"userProperties": [],
				"typeProperties": {
					"dataflow": {
						"referenceName": "DF_BALD0297_BTT_DIM",
						"type": "DataFlowReference"
					},
					"compute": {
						"coreCount": 8,
						"computeType": "General"
					},
					"traceLevel": "Fine"
				}
			},
			{
				"name": "DF_BALD0296_EVALN_ANSWR_DIM",
				"type": "ExecuteDataFlow",
				"dependsOn": [],
				"policy": {
					"timeout": "1.00:00:00",
					"retry": 0,
					"retryIntervalInSeconds": 30,
					"secureOutput": false,
					"secureInput": false
				},
				"userProperties": [],
				"typeProperties": {
					"dataflow": {
						"referenceName": "DF_BALD0296_EVALN_ANSWR_DIM",
						"type": "DataFlowReference"
					},
					"compute": {
						"coreCount": 8,
						"computeType": "General"
					},
					"traceLevel": "Fine"
				}
			},
			{
				"name": "DF_BALD0298_SRVC_PRVDR_DIM",
				"type": "ExecuteDataFlow",
				"dependsOn": [],
				"policy": {
					"timeout": "1.00:00:00",
					"retry": 0,
					"retryIntervalInSeconds": 30,
					"secureOutput": false,
					"secureInput": false
				},
				"userProperties": [],
				"typeProperties": {
					"dataflow": {
						"referenceName": "DF_BALD0298_SRVC_PRVDR_DIM",
						"type": "DataFlowReference"
					},
					"compute": {
						"coreCount": 8,
						"computeType": "General"
					},
					"traceLevel": "Fine"
				}
			}
		],
		"folder": {
			"name": "PGMP"
		},
		"annotations": [],
		"lastPublishTime": "2022-07-18T10:49:25Z"
	},
	"type": "Microsoft.Synapse/workspaces/pipelines"
}